lilio/__init__.py
lilio/_attrs.py
lilio/_bokeh_plots.py
lilio/_plot.py
lilio/calendar.py
lilio/calendar_shifter.py
lilio/calendar_shorthands.py
lilio/resampling.py
lilio/traintest.py
lilio/utils.py
lilio-0.5.0.dist-info/METADATA
lilio-0.5.0.dist-info/WHEEL
lilio-0.5.0.dist-info/licenses/LICENSE
lilio-0.5.0.dist-info/RECORD
