Metadata-Version: 2.3
Name: lilio
Version: 0.5.0
Summary: python package for generating calendars for machine learning timeseries analysis.
Author: Claire Donnelly, Yang Liu, Bart Schilperoort, Peter Kalverla, Jannes van Ingen, Sem Vijverberg
Author-email: c.donnelly@esciencecenter.nl
Maintainer-email: Claire Donnelly <c.donnelly@esciencecenter.nl>, Yang Liu <y.liu@esciencecenter.nl>, Bart Schilperoort <b.schilperoort@esciencecenter.nl>, Peter Kalverla <p.kalvera@esciencecenter.nl>, Jannes van Ingen <jannes.van.ingen@s2s-ai.com>, Sem Vijverberg <sem.vijverberg@vu.nl>
License-Expression: Apache-2.0
License-File: LICENSE
Keywords: calendar,calendar generation,calendar maker,machine learning,timeseries analysis
Classifier: Development Status :: 2 - Pre-Alpha
Classifier: Intended Audience :: Developers
Classifier: License :: OSI Approved :: Apache Software License
Classifier: Natural Language :: English
Classifier: Operating System :: OS Independent
Classifier: Programming Language :: Python
Classifier: Programming Language :: Python :: 3 :: Only
Classifier: Programming Language :: Python :: 3.9
Classifier: Programming Language :: Python :: 3.10
Classifier: Programming Language :: Python :: 3.11
Requires-Python: <3.12,>=3.9
Requires-Dist: matplotlib
Requires-Dist: netcdf4
Requires-Dist: numpy
Requires-Dist: pandas
Requires-Dist: scikit-learn
Requires-Dist: xarray
Provides-Extra: bokeh
Requires-Dist: bokeh>=3.0.0; extra == 'bokeh'
Provides-Extra: dev
Requires-Dist: bump-my-version; extra == 'dev'
Requires-Dist: dask[distributed]; extra == 'dev'
Requires-Dist: hatch; extra == 'dev'
Requires-Dist: mypy; extra == 'dev'
Requires-Dist: pytest; extra == 'dev'
Requires-Dist: pytest-cov; extra == 'dev'
Requires-Dist: ruff; extra == 'dev'
Provides-Extra: docs
Requires-Dist: coverage[toml]; extra == 'docs'
Requires-Dist: ipykernel; extra == 'docs'
Requires-Dist: myst-parser; extra == 'docs'
Requires-Dist: nbsphinx; extra == 'docs'
Requires-Dist: sphinx; extra == 'docs'
Requires-Dist: sphinx-autoapi; extra == 'docs'
Requires-Dist: sphinx-rtd-theme; extra == 'docs'
